{
  "name": "Swayam Singal",
  "handle": "swayam.dev",
  "tagline": "Engines · Sculpts · Stories · Tools",
  "headline": "Engines, sculpts, stories, tools.",
  "headlineSub": "Sometimes all in the same week — engines, characters, fiction, and shipping tools.",
  "bio": "I sculpt worlds in Blender, write speculative fiction, and ship code that bends pixels into meaning. Currently obsessed with the boundary between play and craft.",
  "email": "swayam.singal@gmail.com",
  "phone": "+91 6291465127",
  "github": "https://github.com/swayam8624",
  "linkedin": "https://www.linkedin.com/in/swayamsdomain/",
  "medium": "https://medium.com/@yugenkairo",
  "itch": "https://itch.io",
  "researchgate": "https://researchgate.net",
  "cv": "/cv.pdf",
  "status": {
    "open": true,
    "label": "Open to freelance · Available July 2026"
  }
}
